statbtrfs.py
statbtrfs-0.25.dist-info/METADATA
statbtrfs-0.25.dist-info/WHEEL
statbtrfs-0.25.dist-info/entry_points.txt
statbtrfs-0.25.dist-info/top_level.txt
statbtrfs-0.25.dist-info/RECORD
