Metadata-Version: 2.4
Name: statbtrfs
Version: 0.25
Summary: Query Btrfs filesystem status
Home-page: https://github.com/yufei-pan/statbtrfs
Author: Yufei Pan
Author-email: pan@zopyr.us
License: GPLv3+
Classifier: Programming Language :: Python :: 3
Classifier: License :: OSI Approved :: GNU General Public License v3 or later (GPLv3+)
Classifier: Operating System :: POSIX :: Linux
Requires-Python: >=3.6
Requires-Dist: multiCMD>=1.40
Dynamic: author
Dynamic: author-email
Dynamic: classifier
Dynamic: description
Dynamic: description-content-type
Dynamic: home-page
Dynamic: license
Dynamic: requires-dist
Dynamic: requires-python
Dynamic: summary
